Metadata-Version: 1.0
Name: Sphinx-PyPI-upload
Version: 0.2.1
Summary: setuptools command for uploading Sphinx documentation to PyPI
Home-page: http://bitbucket.org/jezdez/sphinx-pypi-upload/
Author: Jannis Leidel
Author-email: jannis@leidel.info
License: BSD
Download-URL: http://bitbucket.org/jezdez/sphinx-pypi-upload/downloads/
Platform: any
Classifier: Topic :: Documentation
Classifier: Framework :: Setuptools Plugin
Classifier: Development Status :: 4 - Beta
Classifier: Programming Language :: Python
Classifier: Intended Audience :: Developers
Classifier: Operating System :: OS Independent
Classifier: License :: OSI Approved :: BSD License
Classifier: Topic :: Software Development :: Documentation
Classifier: Topic :: Software Development :: Libraries :: Python Modules
